bandcamp_name_your_price_dl.py
bandcamp_name_your_price_dl-0.0.14.dist-info/LICENSE
bandcamp_name_your_price_dl-0.0.14.dist-info/METADATA
bandcamp_name_your_price_dl-0.0.14.dist-info/WHEEL
bandcamp_name_your_price_dl-0.0.14.dist-info/entry_points.txt
bandcamp_name_your_price_dl-0.0.14.dist-info/top_level.txt
bandcamp_name_your_price_dl-0.0.14.dist-info/RECORD
