Metadata-Version: 2.1
Name: bandcamp-name-your-price-dl
Version: 0.0.14
Summary: Automate process of downloading name your price albums from bandcamp.
Home-page: https://github.com/Layerex/bandcamp_name_your_price_dl
Author: Layerex
Author-email: layerex@dismail.de
Classifier: Development Status :: 6 - Mature
Classifier: Environment :: Web Environment
Classifier: Programming Language :: Python :: 3
Classifier: License :: OSI Approved :: GNU General Public License v3 (GPLv3)
Classifier: Operating System :: OS Independent
Classifier: Topic :: Utilities
License-File: LICENSE
Requires-Dist: selenium
Requires-Dist: requests
Requires-Dist: pystandardpaths
